LICENSE
MANIFEST.in
README.md
setup.cfg
setup.py
sparkpost_ip_notifier.egg-info/PKG-INFO
sparkpost_ip_notifier.egg-info/SOURCES.txt
sparkpost_ip_notifier.egg-info/dependency_links.txt
sparkpost_ip_notifier.egg-info/not-zip-safe
sparkpost_ip_notifier.egg-info/requires.txt
sparkpost_ip_notifier.egg-info/top_level.txt
sparkpostipnotifier/__init__.py
sparkpostipnotifier/notifier.py