Metadata-Version: 1.0
Name: sparkpost-ip-notifier
Version: 0.0.1
Summary: Package to notify you by email when your External IP has changed.
Home-page: https://github.com/iktw/sparkpost-ip-notifier
Author: Mohammed Hammoud
Author-email: mohammed@iktw.se
License: MIT licence, see LICENSE
Platform: UNKNOWN
